{
  "PSG": "Paris Saint-Germain",
  "ATM": "Atletico Madrid",
  "BAY": "Bayer Leverkusen",
  "FUL": "Fulham",
  "SEV": "Sevilla",
  "RBL": "RB Leipzig",
  "LAZ": "Lazio",
  "STR": "Strasbourg",
  "EVE": "Everton",
  "MET": "Metz",
  "CHE": "Chelsea",
  "BET": "Real Betis",
  "CRY": "Crystal Palace",
  "HOF": "Hoffenheim",
  "NEW": "Newcastle United",
  "CEL": "Celta Vigo",
  "BMG": "Borussia M.Gladbach",
  "BUR": "Burnley",
  "SOU": "Southampton",
  "FRI": "Freiburg",
  "ARS": "Arsenal",
  "SAS": "Sassuolo",
  "LEI": "Leicester",
  "JUV": "Juventus",
  "VIL": "Villarreal",
  "MCI": "Manchester City",
  "TOT": "Tottenham",
  "ATA": "Atalanta",
  "LEE": "Leeds",
  "LEN": "Lens",
  "LIV": "Liverpool",
  "BAR": "Barcelona",
  "STU": "VfB Stuttgart",
  "SOC": "Real Sociedad",
  "SAM": "Sampdoria",
  "TOR": "Torino",
  "BHA": "Brighton",
  "INT": "Inter",
  "WVW": "Wolverhampton Wanderers",
  "NIC": "Nice",
  "STE": "Saint-Etienne",
  "RMA": "Real Madrid",
  "MIL": "AC Milan",
  "REN": "Rennes",
  "VAL": "Valencia",
  "REI": "Reims",
  "NAP": "Napoli",
  "LIL": "Lille",
  "WOL": "Wolfsburg",
  "EIN": "Eintracht Frankfurt",
  "MON": "Monaco",
  "BRE": "Brest",
  "WHU": "West Ham",
  "MUN": "Manchester United",
  "AVL": "Aston Villa",
  "DOR": "Borussia Dortmund",
  "LYO": "Lyon",
  "ROM": "Roma",
  "MAR": "Marseille",
  "VER": "Verona",
  "MPL": "Montpellier",
  "NAN": "Nantes",
  "UNB": "Union Berlin",
  "GEN": "Genoa",
  "MAI": "Mainz 05",
  "CAG": "Cagliari",
  "BOR": "Bordeaux",
  "SHU": "Sheffield United",
  "ATH": "Athletic Bilbao",
  "UDI": "Udinese",
  "BOL": "Bologna",
  "SCH": "Schalke 04",
  "WER": "Werder Bremen",
  "NIM": "Nimes",
  "ELC": "Elche",
  "ARM": "Arminia Bielefeld",
  "EIB": "Eibar",
  "CRO": "Crotone",
  "ALA": "Deportivo Alaves",
  "FIO": "Fiorentina",
  "AUG": "Augsburg",
  "HUE": "SD Huesca",
  "KOL": "FC Koln",
  "GET": "Getafe",
  "VAD": "Real Valladolid",
  "LOR": "Lorient",
  "LEV": "Levante",
  "HER": "Hertha Berlin",
  "WBA": "West Bromwich Albion",
  "PAR": "Parma Calcio 1913",
  "BEN": "Benevento",
  "ANG": "Angers",
  "GRA": "Granada",
  "DIJ": "Dijon",
  "OSA": "Osasuna",
  "SPE": "Spezia",
  "CAD": "Cadiz"
}
